pxd_admin_extensions/__init__.py
pxd_admin_extensions/annotations.py
pxd_admin_extensions/changelist_template_names.py
pxd_admin_extensions/form_types.py
pxd_admin_extensions/multidb.py
pxd_admin_extensions/contrib/__init__.py
pxd_admin_extensions/contrib/all/__init__.py
pxd_admin_extensions/contrib/all/admin.py
pxd_admin_extensions/contrib/all/apps.py
pxd_admin_extensions/contrib/jet/__init__.py
pxd_admin_extensions/contrib/jet/apps.py
pxd_admin_extensions/contrib/jet/multidb.py
pxd_admin_extensions/contrib/jet/static/admin/extended.css
pxd_admin_extensions/contrib/jet/static/css/admin-numeric-filter.css
pxd_admin_extensions/contrib/jet/templates/admin/base_site.html
pxd_admin_extensions/contrib/jet/templates/admin/filter_numeric_slider.html
pxd_admin_extensions/contrib/jet/templates/admin/stats_change_list.html
pxd_admin_extensions/contrib/jet/templates/admin/stats_list.html
pxd_admin_extensions/contrib/jet/templates/admin/text_input_filter.html
pxd_admin_extensions/contrib/jet/templates/admin/includes/stats/display.html
pxd_admin_extensions/contrib/jet/templates/admin/includes/stats/stats_link.html
pxd_admin_extensions/contrib/jet/templates/admin/includes/stats/wrapper.html
pxd_admin_extensions/contrib/jet/templates/admin_totals/stats_change_list.html
pxd_admin_extensions/contrib/rangefilter/__init__.py
pxd_admin_extensions/contrib/rangefilter/apps.py
pxd_admin_extensions/contrib/rangefilter/filters.py
pxd_admin_extensions/contrib/stats/__init__.py
pxd_admin_extensions/contrib/stats/admin.py
pxd_admin_extensions/contrib/stats/apps.py
pxd_admin_extensions/contrib/stats/const.py
pxd_admin_extensions/contrib/stats/factories.py
pxd_admin_extensions/contrib/stats/utils.py
pxd_admin_extensions/contrib/stats/static/admin/stats/chart.js
pxd_admin_extensions/contrib/stats/static/admin/stats/d3.min.js
pxd_admin_extensions/contrib/stats/static/admin/stats/nv.d3.min.css
pxd_admin_extensions/contrib/stats/static/admin/stats/nv.d3.min.js
preusx_django_admin_extensions-0.1.1.dist-info/LICENSE
preusx_django_admin_extensions-0.1.1.dist-info/METADATA
preusx_django_admin_extensions-0.1.1.dist-info/WHEEL
preusx_django_admin_extensions-0.1.1.dist-info/top_level.txt
preusx_django_admin_extensions-0.1.1.dist-info/RECORD
